{
  "a_comp_cor_00": {
    "CumulativeVarianceExplained": 0.0305511428,
    "Mask": "combined",
    "Method": "aCompCor",
    "Retained": true,
    "SingularValue": 80.3603033354,
    "VarianceExplained": 0.0305511428
  },
  "a_comp_cor_01": {
    "CumulativeVarianceExplained": 0.0544985084,
    "Mask": "combined",
    "Method": "aCompCor",
    "Retained": true,
    "SingularValue": 71.1470192575,
    "VarianceExplained": 0.0239473656
  },
  "a_comp_cor_02": {
    "CumulativeVarianceExplained": 0.07439711,
    "Mask": "combined",
    "Method": "aCompCor",
    "Retained": true,
    "SingularValue": 64.8543508355,
    "VarianceExplained": 0.0198986016
  },
  "a_comp_cor_03": {
    "CumulativeVarianceExplained": 0.0927399054,
    "Mask": "combined",
    "Method": "aCompCor",
    "Retained": true,
    "SingularValue": 62.2673808535,
    "VarianceExplained": 0.0183427954
  },
  "a_comp_cor_04": {
    "CumulativeVarianceExplained": 0.1059802861,
    "Mask": "combined",
    "Method": "aCompCor",
    "Retained": true,
    "SingularValue": 52.9027288813,
    "VarianceExplained": 0.0132403808
  },
  "a_comp_cor_05": {
    "CumulativeVarianceExplained": 0.1177082112,
    "Mask": "combined",
    "Method": "aCompCor",
    "Retained": true,
    "SingularValue": 49.7895761119,
    "VarianceExplained": 0.0117279251
  },
  "a_comp_cor_06": {
    "CumulativeVarianceExplained": 0.1288808585,
    "Mask": "combined",
    "Method": "aCompCor",
    "Retained": true,
    "SingularValue": 48.5965996166,
    "VarianceExplained": 0.0111726473
  },
  "a_comp_cor_07": {
    "CumulativeVarianceExplained": 0.1392842958,
    "Mask": "combined",
    "Method": "aCompCor",
    "Retained": true,
    "SingularValue": 46.8938905012,
    "VarianceExplained": 0.0104034373
  },
  "a_comp_cor_08": {
    "CumulativeVarianceExplained": 0.1492856823,
    "Mask": "combined",
    "Method": "aCompCor",
    "Retained": true,
    "SingularValue": 45.9788329228,
    "VarianceExplained": 0.0100013865
  },
  "a_comp_cor_09": {
    "CumulativeVarianceExplained": 0.159231373,
    "Mask": "combined",
    "Method": "aCompCor",
    "Retained": true,
    "SingularValue": 45.8506304911,
    "VarianceExplained": 0.0099456907
  },
  "a_comp_cor_10": {
    "CumulativeVarianceExplained": 0.1690745399,
    "Mask": "combined",
    "Method": "aCompCor",
    "Retained": true,
    "SingularValue": 45.6136957934,
    "VarianceExplained": 0.0098431669
  },
  "a_comp_cor_11": {
    "CumulativeVarianceExplained": 0.1786329319,
    "Mask": "combined",
    "Method": "aCompCor",
    "Retained": true,
    "SingularValue": 44.9490228311,
    "VarianceExplained": 0.0095583919
  },
  "a_comp_cor_12": {
    "CumulativeVarianceExplained": 0.1881161166,
    "Mask": "combined",
    "Method": "aCompCor",
    "Retained": true,
    "SingularValue": 44.7718398773,
    "VarianceExplained": 0.0094831847
  },
  "a_comp_cor_13": {
    "CumulativeVarianceExplained": 0.1974016279,
    "Mask": "combined",
    "Method": "aCompCor",
    "Retained": true,
    "SingularValue": 44.3027567594,
    "VarianceExplained": 0.0092855114
  },
  "a_comp_cor_14": {
    "CumulativeVarianceExplained": 0.2065437031,
    "Mask": "combined",
    "Method": "aCompCor",
    "Retained": true,
    "SingularValue": 43.9592457676,
    "VarianceExplained": 0.0091420752
  },
  "a_comp_cor_15": {
    "CumulativeVarianceExplained": 0.2155514644,
    "Mask": "combined",
    "Method": "aCompCor",
    "Retained": true,
    "SingularValue": 43.6351296485,
    "VarianceExplained": 0.0090077612
  },
  "a_comp_cor_16": {
    "CumulativeVarianceExplained": 0.2244611867,
    "Mask": "combined",
    "Method": "aCompCor",
    "Retained": true,
    "SingularValue": 43.3970214804,
    "VarianceExplained": 0.0089097224
  },
  "a_comp_cor_17": {
    "CumulativeVarianceExplained": 0.2333006505,
    "Mask": "combined",
    "Method": "aCompCor",
    "Retained": true,
    "SingularValue": 43.2255768828,
    "VarianceExplained": 0.0088394638
  },
  "a_comp_cor_18": {
    "CumulativeVarianceExplained": 0.2420927274,
    "Mask": "combined",
    "Method": "aCompCor",
    "Retained": true,
    "SingularValue": 43.1095585463,
    "VarianceExplained": 0.0087920769
  },
  "a_comp_cor_19": {
    "CumulativeVarianceExplained": 0.2507877232,
    "Mask": "combined",
    "Method": "aCompCor",
    "Retained": true,
    "SingularValue": 42.8708925289,
    "VarianceExplained": 0.0086949958
  },
  "a_comp_cor_20": {
    "CumulativeVarianceExplained": 0.2594306389,
    "Mask": "combined",
    "Method": "aCompCor",
    "Retained": true,
    "SingularValue": 42.7423087301,
    "VarianceExplained": 0.0086429157
  },
  "a_comp_cor_21": {
    "CumulativeVarianceExplained": 0.2679307701,
    "Mask": "combined",
    "Method": "aCompCor",
    "Retained": true,
    "SingularValue": 42.3877781048,
    "VarianceExplained": 0.0085001312
  },
  "a_comp_cor_22": {
    "CumulativeVarianceExplained": 0.2763769145,
    "Mask": "combined",
    "Method": "aCompCor",
    "Retained": true,
    "SingularValue": 42.2529552503,
    "VarianceExplained": 0.0084461444
  },
  "a_comp_cor_23": {
    "CumulativeVarianceExplained": 0.2847637494,
    "Mask": "combined",
    "Method": "aCompCor",
    "Retained": true,
    "SingularValue": 42.1043418691,
    "VarianceExplained": 0.0083868349
  },
  "a_comp_cor_24": {
    "CumulativeVarianceExplained": 0.2930641281,
    "Mask": "combined",
    "Method": "aCompCor",
    "Retained": true,
    "SingularValue": 41.8867622476,
    "VarianceExplained": 0.0083003787
  },
  "a_comp_cor_25": {
    "CumulativeVarianceExplained": 0.3013280015,
    "Mask": "combined",
    "Method": "aCompCor",
    "Retained": true,
    "SingularValue": 41.794551045,
    "VarianceExplained": 0.0082638734
  },
  "a_comp_cor_26": {
    "CumulativeVarianceExplained": 0.30954051,
    "Mask": "combined",
    "Method": "aCompCor",
    "Retained": true,
    "SingularValue": 41.6644597235,
    "VarianceExplained": 0.0082125085
  },
  "a_comp_cor_27": {
    "CumulativeVarianceExplained": 0.317646082,
    "Mask": "combined",
    "Method": "aCompCor",
    "Retained": true,
    "SingularValue": 41.3923108148,
    "VarianceExplained": 0.008105572
  },
  "a_comp_cor_28": {
    "CumulativeVarianceExplained": 0.3256589037,
    "Mask": "combined",
    "Method": "aCompCor",
    "Retained": true,
    "SingularValue": 41.1548076288,
    "VarianceExplained": 0.0080128217
  },
  "a_comp_cor_29": {
    "CumulativeVarianceExplained": 0.333598849,
    "Mask": "combined",
    "Method": "aCompCor",
    "Retained": true,
    "SingularValue": 40.9672293557,
    "VarianceExplained": 0.0079399453
  },
  "a_comp_cor_30": {
    "CumulativeVarianceExplained": 0.3414669955,
    "Mask": "combined",
    "Method": "aCompCor",
    "Retained": true,
    "SingularValue": 40.7815807766,
    "VarianceExplained": 0.0078681465
  },
  "a_comp_cor_31": {
    "CumulativeVarianceExplained": 0.3493030437,
    "Mask": "combined",
    "Method": "aCompCor",
    "Retained": true,
    "SingularValue": 40.6983111201,
    "VarianceExplained": 0.0078360482
  },
  "a_comp_cor_32": {
    "CumulativeVarianceExplained": 0.3571054541,
    "Mask": "combined",
    "Method": "aCompCor",
    "Retained": true,
    "SingularValue": 40.6108641498,
    "VarianceExplained": 0.0078024103
  },
  "a_comp_cor_33": {
    "CumulativeVarianceExplained": 0.3647795482,
    "Mask": "combined",
    "Method": "aCompCor",
    "Retained": true,
    "SingularValue": 40.2755426061,
    "VarianceExplained": 0.0076740942
  },
  "a_comp_cor_34": {
    "CumulativeVarianceExplained": 0.3723814967,
    "Mask": "combined",
    "Method": "aCompCor",
    "Retained": true,
    "SingularValue": 40.0857763626,
    "VarianceExplained": 0.0076019485
  },
  "a_comp_cor_35": {
    "CumulativeVarianceExplained": 0.3799440553,
    "Mask": "combined",
    "Method": "aCompCor",
    "Retained": true,
    "SingularValue": 39.9817881384,
    "VarianceExplained": 0.0075625586
  },
  "a_comp_cor_36": {
    "CumulativeVarianceExplained": 0.3874447332,
    "Mask": "combined",
    "Method": "aCompCor",
    "Retained": true,
    "SingularValue": 39.8178763637,
    "VarianceExplained": 0.0075006778
  },
  "a_comp_cor_37": {
    "CumulativeVarianceExplained": 0.3949082892,
    "Mask": "combined",
    "Method": "aCompCor",
    "Retained": true,
    "SingularValue": 39.7192224131,
    "VarianceExplained": 0.0074635561
  },
  "a_comp_cor_38": {
    "CumulativeVarianceExplained": 0.4023166747,
    "Mask": "combined",
    "Method": "aCompCor",
    "Retained": true,
    "SingularValue": 39.5721479243,
    "VarianceExplained": 0.0074083855
  },
  "a_comp_cor_39": {
    "CumulativeVarianceExplained": 0.4096424258,
    "Mask": "combined",
    "Method": "aCompCor",
    "Retained": true,
    "SingularValue": 39.3508316734,
    "VarianceExplained": 0.007325751
  },
  "a_comp_cor_40": {
    "CumulativeVarianceExplained": 0.4168931613,
    "Mask": "combined",
    "Method": "aCompCor",
    "Retained": true,
    "SingularValue": 39.1488374801,
    "VarianceExplained": 0.0072507355
  },
  "a_comp_cor_41": {
    "CumulativeVarianceExplained": 0.4241013449,
    "Mask": "combined",
    "Method": "aCompCor",
    "Retained": true,
    "SingularValue": 39.0337932703,
    "VarianceExplained": 0.0072081836
  },
  "a_comp_cor_42": {
    "CumulativeVarianceExplained": 0.4312408797,
    "Mask": "combined",
    "Method": "aCompCor",
    "Retained": true,
    "SingularValue": 38.847474855,
    "VarianceExplained": 0.0071395348
  },
  "a_comp_cor_43": {
    "CumulativeVarianceExplained": 0.4383103329,
    "Mask": "combined",
    "Method": "aCompCor",
    "Retained": true,
    "SingularValue": 38.6563414252,
    "VarianceExplained": 0.0070694532
  },
  "a_comp_cor_44": {
    "CumulativeVarianceExplained": 0.4453048977,
    "Mask": "combined",
    "Method": "aCompCor",
    "Retained": true,
    "SingularValue": 38.4510487362,
    "VarianceExplained": 0.0069945649
  },
  "a_comp_cor_45": {
    "CumulativeVarianceExplained": 0.4522946607,
    "Mask": "combined",
    "Method": "aCompCor",
    "Retained": true,
    "SingularValue": 38.4378477258,
    "VarianceExplained": 0.006989763
  },
  "a_comp_cor_46": {
    "CumulativeVarianceExplained": 0.4592202852,
    "Mask": "combined",
    "Method": "aCompCor",
    "Retained": true,
    "SingularValue": 38.261087341,
    "VarianceExplained": 0.0069256245
  },
  "a_comp_cor_47": {
    "CumulativeVarianceExplained": 0.4661127223,
    "Mask": "combined",
    "Method": "aCompCor",
    "Retained": true,
    "SingularValue": 38.1693040481,
    "VarianceExplained": 0.006892437
  },
  "a_comp_cor_48": {
    "CumulativeVarianceExplained": 0.4729317445,
    "Mask": "combined",
    "Method": "aCompCor",
    "Retained": true,
    "SingularValue": 37.9654797255,
    "VarianceExplained": 0.0068190223
  },
  "a_comp_cor_49": {
    "CumulativeVarianceExplained": 0.4797025827,
    "Mask": "combined",
    "Method": "aCompCor",
    "Retained": true,
    "SingularValue": 37.8311075554,
    "VarianceExplained": 0.0067708382
  },
  "a_comp_cor_50": {
    "CumulativeVarianceExplained": 0.4864200675,
    "Mask": "combined",
    "Method": "aCompCor",
    "Retained": true,
    "SingularValue": 37.6817603422,
    "VarianceExplained": 0.0067174848
  },
  "a_comp_cor_51": {
    "CumulativeVarianceExplained": 0.4931100374,
    "Mask": "combined",
    "Method": "aCompCor",
    "Retained": true,
    "SingularValue": 37.604508602,
    "VarianceExplained": 0.0066899699
  },
  "a_comp_cor_52": {
    "CumulativeVarianceExplained": 0.4997197363,
    "Mask": "combined",
    "Method": "aCompCor",
    "Retained": true,
    "SingularValue": 37.3782251447,
    "VarianceExplained": 0.0066096989
  },
  "a_comp_cor_53": {
    "CumulativeVarianceExplained": 0.5062895535,
    "Mask": "combined",
    "Method": "aCompCor",
    "Retained": true,
    "SingularValue": 37.2652879468,
    "VarianceExplained": 0.0065698172
  },
  "aroma_motion_1": {
    "CSFFraction": 0.06,
    "EdgeFraction": 0.56,
    "HighFrequencyContent": 0.05,
    "MaximumRpCorrelation": 0.96,
    "Method": {
      "Name": "ICA-AROMA",
      "Version": "0.4.5"
    },
    "ModelVarianceExplained": 0.0847731745,
    "MotionNoise": true,
    "TotalVarianceExplained": 0.0568427631
  },
  "aroma_motion_10": {
    "CSFFraction": 0.14,
    "EdgeFraction": 0.42,
    "HighFrequencyContent": 0.41,
    "MaximumRpCorrelation": 0.32,
    "Method": {
      "Name": "ICA-AROMA",
      "Version": "0.4.5"
    },
    "ModelVarianceExplained": 0.0369122787,
    "MotionNoise": true,
    "TotalVarianceExplained": 0.0247507059
  },
  "aroma_motion_11": {
    "CSFFraction": 0.01,
    "EdgeFraction": 0.29,
    "HighFrequencyContent": 0.06,
    "MaximumRpCorrelation": 0.37,
    "Method": {
      "Name": "ICA-AROMA",
      "Version": "0.4.5"
    },
    "ModelVarianceExplained": 0.0366669624,
    "MotionNoise": false,
    "TotalVarianceExplained": 0.0245862146
  },
  "aroma_motion_12": {
    "CSFFraction": 0.02,
    "EdgeFraction": 0.32,
    "HighFrequencyContent": 0.11,
    "MaximumRpCorrelation": 0.46,
    "Method": {
      "Name": "ICA-AROMA",
      "Version": "0.4.5"
    },
    "ModelVarianceExplained": 0.0347641886,
    "MotionNoise": false,
    "TotalVarianceExplained": 0.023310352
  },
  "aroma_motion_13": {
    "CSFFraction": 0.01,
    "EdgeFraction": 0.43,
    "HighFrequencyContent": 0.15,
    "MaximumRpCorrelation": 0.6,
    "Method": {
      "Name": "ICA-AROMA",
      "Version": "0.4.5"
    },
    "ModelVarianceExplained": 0.0346852213,
    "MotionNoise": false,
    "TotalVarianceExplained": 0.0232574022
  },
  "aroma_motion_14": {
    "CSFFraction": 0.18,
    "EdgeFraction": 0.39,
    "HighFrequencyContent": 0.42,
    "MaximumRpCorrelation": 0.59,
    "Method": {
      "Name": "ICA-AROMA",
      "Version": "0.4.5"
    },
    "ModelVarianceExplained": 0.0340203052,
    "MotionNoise": true,
    "TotalVarianceExplained": 0.0228115575
  },
  "aroma_motion_15": {
    "CSFFraction": 0.05,
    "EdgeFraction": 0.38,
    "HighFrequencyContent": 0.2,
    "MaximumRpCorrelation": 0.33,
    "Method": {
      "Name": "ICA-AROMA",
      "Version": "0.4.5"
    },
    "ModelVarianceExplained": 0.03353487,
    "MotionNoise": false,
    "TotalVarianceExplained": 0.0224860598
  },
  "aroma_motion_16": {
    "CSFFraction": 0.04,
    "EdgeFraction": 0.56,
    "HighFrequencyContent": 0.28,
    "MaximumRpCorrelation": 0.65,
    "Method": {
      "Name": "ICA-AROMA",
      "Version": "0.4.5"
    },
    "ModelVarianceExplained": 0.0320853046,
    "MotionNoise": true,
    "TotalVarianceExplained": 0.021514086
  },
  "aroma_motion_17": {
    "CSFFraction": 0.18,
    "EdgeFraction": 0.54,
    "HighFrequencyContent": 0.34,
    "MaximumRpCorrelation": 0.55,
    "Method": {
      "Name": "ICA-AROMA",
      "Version": "0.4.5"
    },
    "ModelVarianceExplained": 0.0318297648,
    "MotionNoise": true,
    "TotalVarianceExplained": 0.0213427395
  },
  "aroma_motion_18": {
    "CSFFraction": 0.02,
    "EdgeFraction": 0.33,
    "HighFrequencyContent": 0.15,
    "MaximumRpCorrelation": 0.42,
    "Method": {
      "Name": "ICA-AROMA",
      "Version": "0.4.5"
    },
    "ModelVarianceExplained": 0.0317033455,
    "MotionNoise": false,
    "TotalVarianceExplained": 0.0212579718
  },
  "aroma_motion_19": {
    "CSFFraction": 0.03,
    "EdgeFraction": 0.49,
    "HighFrequencyContent": 0.15,
    "MaximumRpCorrelation": 0.4,
    "Method": {
      "Name": "ICA-AROMA",
      "Version": "0.4.5"
    },
    "ModelVarianceExplained": 0.0312903496,
    "MotionNoise": false,
    "TotalVarianceExplained": 0.0209810467
  },
  "aroma_motion_2": {
    "CSFFraction": 0.05,
    "EdgeFraction": 0.6,
    "HighFrequencyContent": 0.08,
    "MaximumRpCorrelation": 0.94,
    "Method": {
      "Name": "ICA-AROMA",
      "Version": "0.4.5"
    },
    "ModelVarianceExplained": 0.0771952061,
    "MotionNoise": true,
    "TotalVarianceExplained": 0.0517615252
  },
  "aroma_motion_20": {
    "CSFFraction": 0.03,
    "EdgeFraction": 0.31,
    "HighFrequencyContent": 0.15,
    "MaximumRpCorrelation": 0.58,
    "Method": {
      "Name": "ICA-AROMA",
      "Version": "0.4.5"
    },
    "ModelVarianceExplained": 0.0308075501,
    "MotionNoise": false,
    "TotalVarianceExplained": 0.0206573162
  },
  "aroma_motion_21": {
    "CSFFraction": 0.02,
    "EdgeFraction": 0.54,
    "HighFrequencyContent": 0.08,
    "MaximumRpCorrelation": 0.49,
    "Method": {
      "Name": "ICA-AROMA",
      "Version": "0.4.5"
    },
    "ModelVarianceExplained": 0.0304162731,
    "MotionNoise": false,
    "TotalVarianceExplained": 0.0203949541
  },
  "aroma_motion_22": {
    "CSFFraction": 0.18,
    "EdgeFraction": 0.54,
    "HighFrequencyContent": 0.57,
    "MaximumRpCorrelation": 0.44,
    "Method": {
      "Name": "ICA-AROMA",
      "Version": "0.4.5"
    },
    "ModelVarianceExplained": 0.0287855748,
    "MotionNoise": true,
    "TotalVarianceExplained": 0.0193015257
  },
  "aroma_motion_23": {
    "CSFFraction": 0.01,
    "EdgeFraction": 0.49,
    "HighFrequencyContent": 0.17,
    "MaximumRpCorrelation": 0.21,
    "Method": {
      "Name": "ICA-AROMA",
      "Version": "0.4.5"
    },
    "ModelVarianceExplained": 0.0275145863,
    "MotionNoise": false,
    "TotalVarianceExplained": 0.0184492927
  },
  "aroma_motion_24": {
    "CSFFraction": 0.07,
    "EdgeFraction": 0.47,
    "HighFrequencyContent": 0.48,
    "MaximumRpCorrelation": 0.38,
    "Method": {
      "Name": "ICA-AROMA",
      "Version": "0.4.5"
    },
    "ModelVarianceExplained": 0.0274498518,
    "MotionNoise": true,
    "TotalVarianceExplained": 0.0184058864
  },
  "aroma_motion_25": {
    "CSFFraction": 0.01,
    "EdgeFraction": 0.19,
    "HighFrequencyContent": 0.17,
    "MaximumRpCorrelation": 0.34,
    "Method": {
      "Name": "ICA-AROMA",
      "Version": "0.4.5"
    },
    "ModelVarianceExplained": 0.0260137982,
    "MotionNoise": false,
    "TotalVarianceExplained": 0.0174429727
  },
  "aroma_motion_26": {
    "CSFFraction": 0.05,
    "EdgeFraction": 0.49,
    "HighFrequencyContent": 0.18,
    "MaximumRpCorrelation": 0.49,
    "Method": {
      "Name": "ICA-AROMA",
      "Version": "0.4.5"
    },
    "ModelVarianceExplained": 0.0251579193,
    "MotionNoise": false,
    "TotalVarianceExplained": 0.0168690822
  },
  "aroma_motion_3": {
    "CSFFraction": 0.01,
    "EdgeFraction": 0.52,
    "HighFrequencyContent": 0.04,
    "MaximumRpCorrelation": 0.63,
    "Method": {
      "Name": "ICA-AROMA",
      "Version": "0.4.5"
    },
    "ModelVarianceExplained": 0.0547070378,
    "MotionNoise": false,
    "TotalVarianceExplained": 0.0366825851
  },
  "aroma_motion_4": {
    "CSFFraction": 0.09,
    "EdgeFraction": 0.53,
    "HighFrequencyContent": 0.24,
    "MaximumRpCorrelation": 0.8,
    "Method": {
      "Name": "ICA-AROMA",
      "Version": "0.4.5"
    },
    "ModelVarianceExplained": 0.0474963566,
    "MotionNoise": true,
    "TotalVarianceExplained": 0.0318476235
  },
  "aroma_motion_5": {
    "CSFFraction": 0.2,
    "EdgeFraction": 0.64,
    "HighFrequencyContent": 0.12,
    "MaximumRpCorrelation": 0.82,
    "Method": {
      "Name": "ICA-AROMA",
      "Version": "0.4.5"
    },
    "ModelVarianceExplained": 0.0441698285,
    "MotionNoise": true,
    "TotalVarianceExplained": 0.0296170942
  },
  "aroma_motion_6": {
    "CSFFraction": 0.05,
    "EdgeFraction": 0.52,
    "HighFrequencyContent": 0.42,
    "MaximumRpCorrelation": 0.76,
    "Method": {
      "Name": "ICA-AROMA",
      "Version": "0.4.5"
    },
    "ModelVarianceExplained": 0.0403458382,
    "MotionNoise": true,
    "TotalVarianceExplained": 0.0270530028
  },
  "aroma_motion_7": {
    "CSFFraction": 0.29,
    "EdgeFraction": 0.61,
    "HighFrequencyContent": 0.46,
    "MaximumRpCorrelation": 0.3,
    "Method": {
      "Name": "ICA-AROMA",
      "Version": "0.4.5"
    },
    "ModelVarianceExplained": 0.0402182578,
    "MotionNoise": true,
    "TotalVarianceExplained": 0.0269674565
  },
  "aroma_motion_8": {
    "CSFFraction": 0.27,
    "EdgeFraction": 0.73,
    "HighFrequencyContent": 0.38,
    "MaximumRpCorrelation": 0.35,
    "Method": {
      "Name": "ICA-AROMA",
      "Version": "0.4.5"
    },
    "ModelVarianceExplained": 0.0390224036,
    "MotionNoise": true,
    "TotalVarianceExplained": 0.0261656032
  },
  "aroma_motion_9": {
    "CSFFraction": 0.11,
    "EdgeFraction": 0.67,
    "HighFrequencyContent": 0.2,
    "MaximumRpCorrelation": 0.31,
    "Method": {
      "Name": "ICA-AROMA",
      "Version": "0.4.5"
    },
    "ModelVarianceExplained": 0.0384337527,
    "MotionNoise": true,
    "TotalVarianceExplained": 0.0257708964
  },
  "c_comp_cor_00": {
    "CumulativeVarianceExplained": 0.1342282077,
    "Mask": "CSF",
    "Method": "aCompCor",
    "Retained": true,
    "SingularValue": 57.3040912453,
    "VarianceExplained": 0.1342282077
  },
  "c_comp_cor_01": {
    "CumulativeVarianceExplained": 0.2206731581,
    "Mask": "CSF",
    "Method": "aCompCor",
    "Retained": true,
    "SingularValue": 45.9868379668,
    "VarianceExplained": 0.0864449504
  },
  "c_comp_cor_02": {
    "CumulativeVarianceExplained": 0.2943283182,
    "Mask": "CSF",
    "Method": "aCompCor",
    "Retained": true,
    "SingularValue": 42.4487907511,
    "VarianceExplained": 0.0736551601
  },
  "c_comp_cor_03": {
    "CumulativeVarianceExplained": 0.3479223101,
    "Mask": "CSF",
    "Method": "aCompCor",
    "Retained": true,
    "SingularValue": 36.2094382366,
    "VarianceExplained": 0.0535939919
  },
  "c_comp_cor_04": {
    "CumulativeVarianceExplained": 0.3912065543,
    "Mask": "CSF",
    "Method": "aCompCor",
    "Retained": true,
    "SingularValue": 32.5408320553,
    "VarianceExplained": 0.0432842442
  },
  "c_comp_cor_05": {
    "CumulativeVarianceExplained": 0.4232171259,
    "Mask": "CSF",
    "Method": "aCompCor",
    "Retained": true,
    "SingularValue": 27.9840423035,
    "VarianceExplained": 0.0320105716
  },
  "c_comp_cor_06": {
    "CumulativeVarianceExplained": 0.4547780598,
    "Mask": "CSF",
    "Method": "aCompCor",
    "Retained": true,
    "SingularValue": 27.7868077888,
    "VarianceExplained": 0.0315609339
  },
  "c_comp_cor_07": {
    "CumulativeVarianceExplained": 0.4795031684,
    "Mask": "CSF",
    "Method": "aCompCor",
    "Retained": true,
    "SingularValue": 24.5942078029,
    "VarianceExplained": 0.0247251086
  },
  "c_comp_cor_08": {
    "CumulativeVarianceExplained": 0.5026090081,
    "Mask": "CSF",
    "Method": "aCompCor",
    "Retained": true,
    "SingularValue": 23.7752236738,
    "VarianceExplained": 0.0231058396
  },
  "csf": {
    "Method": "Mean"
  },
  "csf_wm": {
    "Method": "Mean"
  },
  "global_signal": {
    "Method": "Mean"
  },
  "t_comp_cor_00": {
    "CumulativeVarianceExplained": 0.1543291325,
    "Method": "tCompCor",
    "Retained": true,
    "SingularValue": 126.054462357,
    "VarianceExplained": 0.1543291325
  },
  "t_comp_cor_01": {
    "CumulativeVarianceExplained": 0.2767600148,
    "Method": "tCompCor",
    "Retained": true,
    "SingularValue": 112.2741450187,
    "VarianceExplained": 0.1224308823
  },
  "t_comp_cor_02": {
    "CumulativeVarianceExplained": 0.3938540425,
    "Method": "tCompCor",
    "Retained": true,
    "SingularValue": 109.7998228599,
    "VarianceExplained": 0.1170940278
  },
  "t_comp_cor_03": {
    "CumulativeVarianceExplained": 0.4724414234,
    "Method": "tCompCor",
    "Retained": true,
    "SingularValue": 89.9519690388,
    "VarianceExplained": 0.0785873809
  },
  "t_comp_cor_04": {
    "CumulativeVarianceExplained": 0.5066540569,
    "Method": "tCompCor",
    "Retained": true,
    "SingularValue": 59.350928794,
    "VarianceExplained": 0.0342126335
  },
  "tcompcor": {
    "Method": "Mean"
  },
  "w_comp_cor_00": {
    "CumulativeVarianceExplained": 0.0229410862,
    "Mask": "WM",
    "Method": "aCompCor",
    "Retained": true,
    "SingularValue": 61.0138996077,
    "VarianceExplained": 0.0229410862
  },
  "w_comp_cor_01": {
    "CumulativeVarianceExplained": 0.039689574,
    "Mask": "WM",
    "Method": "aCompCor",
    "Retained": true,
    "SingularValue": 52.1326252257,
    "VarianceExplained": 0.0167484878
  },
  "w_comp_cor_02": {
    "CumulativeVarianceExplained": 0.0530551175,
    "Mask": "WM",
    "Method": "aCompCor",
    "Retained": true,
    "SingularValue": 46.5709508499,
    "VarianceExplained": 0.0133655434
  },
  "w_comp_cor_03": {
    "CumulativeVarianceExplained": 0.0654083962,
    "Mask": "WM",
    "Method": "aCompCor",
    "Retained": true,
    "SingularValue": 44.7726618937,
    "VarianceExplained": 0.0123532788
  },
  "w_comp_cor_04": {
    "CumulativeVarianceExplained": 0.0768900824,
    "Mask": "WM",
    "Method": "aCompCor",
    "Retained": true,
    "SingularValue": 43.1642929175,
    "VarianceExplained": 0.0114816862
  },
  "w_comp_cor_05": {
    "CumulativeVarianceExplained": 0.0880444675,
    "Mask": "WM",
    "Method": "aCompCor",
    "Retained": true,
    "SingularValue": 42.5446162162,
    "VarianceExplained": 0.011154385
  },
  "w_comp_cor_06": {
    "CumulativeVarianceExplained": 0.0990604163,
    "Mask": "WM",
    "Method": "aCompCor",
    "Retained": true,
    "SingularValue": 42.2797830233,
    "VarianceExplained": 0.0110159489
  },
  "w_comp_cor_07": {
    "CumulativeVarianceExplained": 0.1098136355,
    "Mask": "WM",
    "Method": "aCompCor",
    "Retained": true,
    "SingularValue": 41.7725554252,
    "VarianceExplained": 0.0107532192
  },
  "w_comp_cor_08": {
    "CumulativeVarianceExplained": 0.1204479974,
    "Mask": "WM",
    "Method": "aCompCor",
    "Retained": true,
    "SingularValue": 41.5410539649,
    "VarianceExplained": 0.0106343618
  },
  "w_comp_cor_09": {
    "CumulativeVarianceExplained": 0.1308898283,
    "Mask": "WM",
    "Method": "aCompCor",
    "Retained": true,
    "SingularValue": 41.1632942617,
    "VarianceExplained": 0.010441831
  },
  "w_comp_cor_10": {
    "CumulativeVarianceExplained": 0.1412224382,
    "Mask": "WM",
    "Method": "aCompCor",
    "Retained": true,
    "SingularValue": 40.9474452767,
    "VarianceExplained": 0.0103326099
  },
  "w_comp_cor_11": {
    "CumulativeVarianceExplained": 0.1513642106,
    "Mask": "WM",
    "Method": "aCompCor",
    "Retained": true,
    "SingularValue": 40.5675446608,
    "VarianceExplained": 0.0101417723
  },
  "w_comp_cor_12": {
    "CumulativeVarianceExplained": 0.1614137817,
    "Mask": "WM",
    "Method": "aCompCor",
    "Retained": true,
    "SingularValue": 40.3827192177,
    "VarianceExplained": 0.0100495712
  },
  "w_comp_cor_13": {
    "CumulativeVarianceExplained": 0.171273944,
    "Mask": "WM",
    "Method": "aCompCor",
    "Retained": true,
    "SingularValue": 40.0003531465,
    "VarianceExplained": 0.0098601623
  },
  "w_comp_cor_14": {
    "CumulativeVarianceExplained": 0.1810664853,
    "Mask": "WM",
    "Method": "aCompCor",
    "Retained": true,
    "SingularValue": 39.8629559445,
    "VarianceExplained": 0.0097925413
  },
  "w_comp_cor_15": {
    "CumulativeVarianceExplained": 0.1907820569,
    "Mask": "WM",
    "Method": "aCompCor",
    "Retained": true,
    "SingularValue": 39.7059848478,
    "VarianceExplained": 0.0097155716
  },
  "w_comp_cor_16": {
    "CumulativeVarianceExplained": 0.200312148,
    "Mask": "WM",
    "Method": "aCompCor",
    "Retained": true,
    "SingularValue": 39.3251440593,
    "VarianceExplained": 0.0095300912
  },
  "w_comp_cor_17": {
    "CumulativeVarianceExplained": 0.209821073,
    "Mask": "WM",
    "Method": "aCompCor",
    "Retained": true,
    "SingularValue": 39.2814493722,
    "VarianceExplained": 0.0095089249
  },
  "w_comp_cor_18": {
    "CumulativeVarianceExplained": 0.2192590436,
    "Mask": "WM",
    "Method": "aCompCor",
    "Retained": true,
    "SingularValue": 39.1346186286,
    "VarianceExplained": 0.0094379707
  },
  "w_comp_cor_19": {
    "CumulativeVarianceExplained": 0.2286323513,
    "Mask": "WM",
    "Method": "aCompCor",
    "Retained": true,
    "SingularValue": 39.0003253941,
    "VarianceExplained": 0.0093733077
  },
  "w_comp_cor_20": {
    "CumulativeVarianceExplained": 0.2378471555,
    "Mask": "WM",
    "Method": "aCompCor",
    "Retained": true,
    "SingularValue": 38.669169939,
    "VarianceExplained": 0.0092148042
  },
  "w_comp_cor_21": {
    "CumulativeVarianceExplained": 0.2469820259,
    "Mask": "WM",
    "Method": "aCompCor",
    "Retained": true,
    "SingularValue": 38.5010868968,
    "VarianceExplained": 0.0091348704
  },
  "w_comp_cor_22": {
    "CumulativeVarianceExplained": 0.2560388586,
    "Mask": "WM",
    "Method": "aCompCor",
    "Retained": true,
    "SingularValue": 38.3362799767,
    "VarianceExplained": 0.0090568327
  },
  "w_comp_cor_23": {
    "CumulativeVarianceExplained": 0.2650401952,
    "Mask": "WM",
    "Method": "aCompCor",
    "Retained": true,
    "SingularValue": 38.218645811,
    "VarianceExplained": 0.0090013366
  },
  "w_comp_cor_24": {
    "CumulativeVarianceExplained": 0.2739490365,
    "Mask": "WM",
    "Method": "aCompCor",
    "Retained": true,
    "SingularValue": 38.0217765857,
    "VarianceExplained": 0.0089088413
  },
  "w_comp_cor_25": {
    "CumulativeVarianceExplained": 0.2827763447,
    "Mask": "WM",
    "Method": "aCompCor",
    "Retained": true,
    "SingularValue": 37.847390427,
    "VarianceExplained": 0.0088273082
  },
  "w_comp_cor_26": {
    "CumulativeVarianceExplained": 0.2915040417,
    "Mask": "WM",
    "Method": "aCompCor",
    "Retained": true,
    "SingularValue": 37.6332412254,
    "VarianceExplained": 0.008727697
  },
  "w_comp_cor_27": {
    "CumulativeVarianceExplained": 0.3001452047,
    "Mask": "WM",
    "Method": "aCompCor",
    "Retained": true,
    "SingularValue": 37.4462121151,
    "VarianceExplained": 0.008641163
  },
  "w_comp_cor_28": {
    "CumulativeVarianceExplained": 0.3086935217,
    "Mask": "WM",
    "Method": "aCompCor",
    "Retained": true,
    "SingularValue": 37.2444962418,
    "VarianceExplained": 0.008548317
  },
  "w_comp_cor_29": {
    "CumulativeVarianceExplained": 0.3171680577,
    "Mask": "WM",
    "Method": "aCompCor",
    "Retained": true,
    "SingularValue": 37.0834180794,
    "VarianceExplained": 0.0084745359
  },
  "w_comp_cor_30": {
    "CumulativeVarianceExplained": 0.3255978756,
    "Mask": "WM",
    "Method": "aCompCor",
    "Retained": true,
    "SingularValue": 36.9854487739,
    "VarianceExplained": 0.008429818
  },
  "w_comp_cor_31": {
    "CumulativeVarianceExplained": 0.3339245222,
    "Mask": "WM",
    "Method": "aCompCor",
    "Retained": true,
    "SingularValue": 36.7584219535,
    "VarianceExplained": 0.0083266465
  },
  "w_comp_cor_32": {
    "CumulativeVarianceExplained": 0.3421714211,
    "Mask": "WM",
    "Method": "aCompCor",
    "Retained": true,
    "SingularValue": 36.5819734692,
    "VarianceExplained": 0.0082468989
  },
  "w_comp_cor_33": {
    "CumulativeVarianceExplained": 0.3503420193,
    "Mask": "WM",
    "Method": "aCompCor",
    "Retained": true,
    "SingularValue": 36.4123511187,
    "VarianceExplained": 0.0081705982
  },
  "w_comp_cor_34": {
    "CumulativeVarianceExplained": 0.358389543,
    "Mask": "WM",
    "Method": "aCompCor",
    "Retained": true,
    "SingularValue": 36.1370690679,
    "VarianceExplained": 0.0080475237
  },
  "w_comp_cor_35": {
    "CumulativeVarianceExplained": 0.3664252404,
    "Mask": "WM",
    "Method": "aCompCor",
    "Retained": true,
    "SingularValue": 36.1105066662,
    "VarianceExplained": 0.0080356974
  },
  "w_comp_cor_36": {
    "CumulativeVarianceExplained": 0.3743695974,
    "Mask": "WM",
    "Method": "aCompCor",
    "Retained": true,
    "SingularValue": 35.9046890479,
    "VarianceExplained": 0.007944357
  },
  "w_comp_cor_37": {
    "CumulativeVarianceExplained": 0.3822578822,
    "Mask": "WM",
    "Method": "aCompCor",
    "Retained": true,
    "SingularValue": 35.7777550905,
    "VarianceExplained": 0.0078882849
  },
  "w_comp_cor_38": {
    "CumulativeVarianceExplained": 0.3901240269,
    "Mask": "WM",
    "Method": "aCompCor",
    "Retained": true,
    "SingularValue": 35.7275108418,
    "VarianceExplained": 0.0078661447
  },
  "w_comp_cor_39": {
    "CumulativeVarianceExplained": 0.3979581286,
    "Mask": "WM",
    "Method": "aCompCor",
    "Retained": true,
    "SingularValue": 35.6546678962,
    "VarianceExplained": 0.0078341016
  },
  "w_comp_cor_40": {
    "CumulativeVarianceExplained": 0.4057167631,
    "Mask": "WM",
    "Method": "aCompCor",
    "Retained": true,
    "SingularValue": 35.4825187575,
    "VarianceExplained": 0.0077586345
  },
  "w_comp_cor_41": {
    "CumulativeVarianceExplained": 0.4133794253,
    "Mask": "WM",
    "Method": "aCompCor",
    "Retained": true,
    "SingularValue": 35.2623810776,
    "VarianceExplained": 0.0076626622
  },
  "w_comp_cor_42": {
    "CumulativeVarianceExplained": 0.4209948006,
    "Mask": "WM",
    "Method": "aCompCor",
    "Retained": true,
    "SingularValue": 35.1534093839,
    "VarianceExplained": 0.0076153754
  },
  "w_comp_cor_43": {
    "CumulativeVarianceExplained": 0.4285722303,
    "Mask": "WM",
    "Method": "aCompCor",
    "Retained": true,
    "SingularValue": 35.0657193393,
    "VarianceExplained": 0.0075774297
  },
  "w_comp_cor_44": {
    "CumulativeVarianceExplained": 0.4360545806,
    "Mask": "WM",
    "Method": "aCompCor",
    "Retained": true,
    "SingularValue": 34.8450275011,
    "VarianceExplained": 0.0074823503
  },
  "w_comp_cor_45": {
    "CumulativeVarianceExplained": 0.4434853746,
    "Mask": "WM",
    "Method": "aCompCor",
    "Retained": true,
    "SingularValue": 34.7247722671,
    "VarianceExplained": 0.007430794
  },
  "w_comp_cor_46": {
    "CumulativeVarianceExplained": 0.4508547319,
    "Mask": "WM",
    "Method": "aCompCor",
    "Retained": true,
    "SingularValue": 34.5809245848,
    "VarianceExplained": 0.0073693573
  },
  "w_comp_cor_47": {
    "CumulativeVarianceExplained": 0.4581029565,
    "Mask": "WM",
    "Method": "aCompCor",
    "Retained": true,
    "SingularValue": 34.2955377081,
    "VarianceExplained": 0.0072482246
  },
  "w_comp_cor_48": {
    "CumulativeVarianceExplained": 0.4653460427,
    "Mask": "WM",
    "Method": "aCompCor",
    "Retained": true,
    "SingularValue": 34.2833790755,
    "VarianceExplained": 0.0072430862
  },
  "w_comp_cor_49": {
    "CumulativeVarianceExplained": 0.4724911766,
    "Mask": "WM",
    "Method": "aCompCor",
    "Retained": true,
    "SingularValue": 34.0507732692,
    "VarianceExplained": 0.0071451339
  },
  "w_comp_cor_50": {
    "CumulativeVarianceExplained": 0.4796026544,
    "Mask": "WM",
    "Method": "aCompCor",
    "Retained": true,
    "SingularValue": 33.9704833325,
    "VarianceExplained": 0.0071114779
  },
  "w_comp_cor_51": {
    "CumulativeVarianceExplained": 0.4866559351,
    "Mask": "WM",
    "Method": "aCompCor",
    "Retained": true,
    "SingularValue": 33.8311980976,
    "VarianceExplained": 0.0070532807
  },
  "w_comp_cor_52": {
    "CumulativeVarianceExplained": 0.4936688907,
    "Mask": "WM",
    "Method": "aCompCor",
    "Retained": true,
    "SingularValue": 33.7343492576,
    "VarianceExplained": 0.0070129555
  },
  "w_comp_cor_53": {
    "CumulativeVarianceExplained": 0.5006560303,
    "Mask": "WM",
    "Method": "aCompCor",
    "Retained": true,
    "SingularValue": 33.6722010178,
    "VarianceExplained": 0.0069871396
  },
  "white_matter": {
    "Method": "Mean"
  }
}